oblique_classifier_1-0.3.0.dist-info/licenses/LICENSE
oc1/__init__.py
oc1/core/__init__.py
oc1/core/hill_climb.py
oc1/core/logging.py
oc1/core/node.py
oc1/core/splits.py
oc1/core/tree.py
oc1/data/__init__.py
oc1/data/datasets.py
oc1/evaluation/__init__.py
oc1/visualization/__init__.py
oblique_classifier_1-0.3.0.dist-info/METADATA
oblique_classifier_1-0.3.0.dist-info/WHEEL
oblique_classifier_1-0.3.0.dist-info/top_level.txt
oblique_classifier_1-0.3.0.dist-info/RECORD
