Metadata-Version: 2.4
Name: oblique-classifier-1
Version: 0.3.0
Summary: OC1 Oblique Decision Tree - Implementation of Murthy et al. (AAAI-1992)
Home-page: https://github.com/HxRJILI/Oblique-Classifier-1
Author: Fatima-Ezzahrae AKEBLI, Yasser
Author-email: RJILI Houssam <houssam.rjili@example.com>
Maintainer-email: RJILI Houssam <houssam.rjili@example.com>
License: MIT
Project-URL: Homepage, https://github.com/HxRJILI/Oblique-Classifier-1
Project-URL: Documentation, https://github.com/HxRJILI/Oblique-Classifier-1#readme
Project-URL: Repository, https://github.com/HxRJILI/Oblique-Classifier-1.git
Project-URL: Issues, https://github.com/HxRJILI/Oblique-Classifier-1/issues
Keywords: machine-learning,decision-tree,oblique-tree,classification,oc1,murthy
Classifier: Development Status :: 4 - Beta
Classifier: Intended Audience :: Science/Research
Classifier: Intended Audience :: Developers
Classifier: Intended Audience :: Education
Classifier: License :: OSI Approved :: MIT License
Classifier: Operating System :: OS Independent
Classifier: Programming Language :: Python :: 3
Classifier: Programming Language :: Python :: 3.8
Classifier: Programming Language :: Python :: 3.9
Classifier: Programming Language :: Python :: 3.10
Classifier: Programming Language :: Python :: 3.11
Classifier: Programming Language :: Python :: 3.12
Classifier: Topic :: Scientific/Engineering :: Artificial Intelligence
Classifier: Topic :: Scientific/Engineering :: Information Analysis
Requires-Python: >=3.8
License-File: LICENSE
Requires-Dist: numpy>=1.20.0
Provides-Extra: dev
Requires-Dist: pytest>=7.0.0; extra == "dev"
Requires-Dist: pytest-cov>=4.0.0; extra == "dev"
Requires-Dist: build; extra == "dev"
Requires-Dist: twine; extra == "dev"
Provides-Extra: viz
Requires-Dist: matplotlib>=3.5.0; extra == "viz"
Dynamic: home-page
Dynamic: license-file
Dynamic: requires-python
